db/__init__.py
mega_pack_pbf_parser/__init__.py
mega_pack_pbf_parser/config_manager.py
mega_pack_pbf_parser/config_manager_old.py
mega_pack_pbf_parser/constants.py
mega_pack_pbf_parser/db_tools.py
mega_pack_pbf_parser/dev-1.py
mega_pack_pbf_parser/dev.py
mega_pack_pbf_parser/exceptions.py
mega_pack_pbf_parser/get_report_data.py
mega_pack_pbf_parser/project_parser.py
mega_pack_pbf_parser/queries.py
mega_pack_pbf_parser/utils.py
mega_pack_pbf_parser/data/__init__.py
mega_pack_pbf_parser/data/create_database.sql
mega_pack_pbf_parser/data/packs_pbf_type.csv
mega_pack_pbf_parser/data/pbf.sqbpro
mega_pack_pbf_parser/exceptions/__init__.py
mega_pack_pbf_parser/exceptions/exceptions.py
mega_pack_pbf_parser/jinja/__init__.py
mega_pack_pbf_parser/parsers/__init__.py
mega_pack_pbf_parser/parsers/project_parser.py
mega_pack_pbf_parser/tasks/__init__.py
mega_pack_pbf_parser/tasks/get_product_pbf_name_dict.py
mega_pack_pbf_parser/tasks/get_total_song_count.py
mega_pack_pbf_parser/tasks/parse_pbf_folder.py
mega_pack_pbf_parser/templates/__init__.py
mega_pack_pbf_parser/tools/__init__.py
mega_pack_pbf_parser/tools/constants.py
mega_pack_pbf_parser/tools/db_tools.py
mega_pack_pbf_parser/tools/queries.py
mega_pack_pbf_parser/tools/utils.py
mega_pack_pbf_parser-0.1.8.dist-info/LICENSE
mega_pack_pbf_parser-0.1.8.dist-info/METADATA
mega_pack_pbf_parser-0.1.8.dist-info/WHEEL
mega_pack_pbf_parser-0.1.8.dist-info/top_level.txt
mega_pack_pbf_parser-0.1.8.dist-info/RECORD
