Metadata-Version: 2.1
Name: mega_pack_pbf_parser
Version: 0.1.8
Summary: Collects song information from BB Projects
Home-page: https://github.com/rjcannizzo/mega-pack-pbf-parser
Author: John Nastala
License-File: LICENSE
